{
  "main": {
    "id": "d3c4fc27ca7b0df8",
    "type": "split",
    "children": [
      {
        "id": "88ba9532afa5181f",
        "type": "tabs",
        "children": [
          {
            "id": "38d5f04da6d2d7c5",
            "type": "leaf",
            "state": {
              "type": "empty",
              "state": {},
              "icon": "lucide-file",
              "title": "New tab"
            }
          }
        ]
      }
    ],
    "direction": "vertical"
  },
  "left": {
    "id": "b37d0046ba283c57",
    "type": "mobile-drawer",
    "children": [
      {
        "id": "6dd3ff7deea29343",
        "type": "leaf",
        "state": {
          "type": "file-explorer",
          "state": {
            "sortOrder": "alphabetical",
            "autoReveal": false
          },
          "icon": "lucide-folder-closed",
          "title": "Files"
        }
      },
      {
        "id": "18101c88f11ff145",
        "type": "leaf",
        "state": {
          "type": "search",
          "state": {
            "query": "",
            "matchingCase": false,
            "explainSearch": false,
            "collapseAll": false,
            "extraContext": false,
            "sortOrder": "alphabetical"
          },
          "icon": "lucide-search",
          "title": "Search"
        }
      },
      {
        "id": "5a73b26299b98565",
        "type": "leaf",
        "state": {
          "type": "tag",
          "state": {
            "sortOrder": "frequency",
            "useHierarchy": true,
            "showSearch": false,
            "searchQuery": ""
          },
          "icon": "lucide-tags",
          "title": "Tags"
        }
      },
      {
        "id": "ca2238fc7585b9f7",
        "type": "leaf",
        "state": {
          "type": "all-properties",
          "state": {
            "sortOrder": "frequency",
            "showSearch": false,
            "searchQuery": ""
          },
          "icon": "lucide-archive",
          "title": "All properties"
        }
      },
      {
        "id": "ad9f9474a24a9321",
        "type": "leaf",
        "state": {
          "type": "bookmarks",
          "state": {},
          "icon": "lucide-bookmark",
          "title": "Bookmarks"
        }
      }
    ],
    "currentTab": 0
  },
  "right": {
    "id": "d1afdfdfcd6994f6",
    "type": "mobile-drawer",
    "children": [
      {
        "id": "784417fe7a910a14",
        "type": "leaf",
        "state": {
          "type": "backlink",
          "state": {
            "file": "2-1/EMF/Energy_and_Boundary_Conditions.md",
            "collapseAll": false,
            "extraContext": false,
            "sortOrder": "alphabetical",
            "showSearch": false,
            "searchQuery": "",
            "backlinkCollapsed": false,
            "unlinkedCollapsed": true
          },
          "icon": "links-coming-in",
          "title": "Backlinks"
        }
      },
      {
        "id": "7120ff2f133f9610",
        "type": "leaf",
        "state": {
          "type": "outgoing-link",
          "state": {
            "file": "Untitled.base",
            "linksCollapsed": false,
            "unlinkedCollapsed": true
          },
          "icon": "links-going-out",
          "title": "Outgoing links"
        }
      },
      {
        "id": "d01c94a20c33f412",
        "type": "leaf",
        "state": {
          "type": "outline",
          "state": {
            "file": "Untitled.base",
            "followCursor": false,
            "showSearch": false,
            "searchQuery": ""
          },
          "icon": "lucide-list",
          "title": "Outline"
        }
      },
      {
        "id": "e02bc37d6c4a010a",
        "type": "leaf",
        "state": {
          "type": "git-view",
          "state": {},
          "icon": "git-pull-request",
          "title": "Source Control"
        }
      }
    ],
    "currentTab": 3
  },
  "left-ribbon": {
    "hiddenItems": {
      "markdown-importer:Open format converter": false,
      "switcher:Open quick switcher": false,
      "graph:Open graph view": false,
      "canvas:Create new canvas": false,
      "daily-notes:Open today's daily note": false,
      "templates:Insert template": false,
      "command-palette:Open command palette": false,
      "bases:Create new base": false,
      "obsidian-git:Open Git source control": false
    }
  },
  "active": "38d5f04da6d2d7c5",
  "lastOpenFiles": [
    "2-1/Electronics 2/Test.md",
    "2-1/Electronics 2/Op Amp QnA.md",
    "2-1/Electronics 2/attachments/Pasted image 20260107051819.png",
    "2-1/Electronics 2/attachments/Pasted image 20260107051222.png",
    "2-1/Electronics 2/attachments/Pasted image 20260107045301.png",
    "2-1/Electronics 2/attachments/Pasted image 20260107044952.png",
    "/2-1/Electronics 2/attachments/Pasted image 20260107051819.png",
    "/2-1/Electronics 2/attachments/Pasted image 20260107051222.png",
    "/2-1/Electronics 2/attachments/Pasted image 20260107045301.png",
    "/2-1/Electronics 2/attachments/Pasted image 20260107044952.png",
    "/2-1/Electronics 2/attachments/Pasted image 20260107015603.png",
    "2-1/Electronics 2/attachments/Pasted image 20260107015603.png",
    "/2-1/Electronics 2/attachments",
    "/2-1/Electronics 2/Op Amp QnA.md",
    "/2-1/Electronics 2",
    "/2-1",
    "2-1/Electronics 2/attachments/capture_temp",
    "Untitled.md",
    "README.md",
    "Untitled.canvas",
    "2-1/Electronics 2/Untitled.base",
    "2-1/Electronics 2/Op Amp.md",
    "capture_temp.md",
    "capture_temp",
    "/2-1/Electronics 2/Op Amp.md",
    "2-1/Electronics 2/attachments",
    "2-1/Electronics 2",
    "/2-1/EMF",
    "2-1/EMF/EMF_Explanation_Full.md",
    "2-1/EMF/EMF_Explanation_1_2.md",
    "2-1/EMF/Untitled.md",
    "2-1/EMF/Energy_and_Boundary_Conditions.md",
    "/2-1/EMF/Energy_and_Boundary_Conditions.md",
    "Academic Prompt.md",
    "Untitled 3.md",
    "Untitled 1.md",
    "Untitled 2.md",
    "2-1/EMF",
    "Test.md",
    "Insight.md",
    "/Untitled.md",
    "/Insight.md",
    "/Academic Prompt.md",
    "Unsorted/Untitled.md",
    "Unsorted/unsorted link.md",
    "/Unsorted/Untitled.md",
    "/Unsorted/unsorted link.md"
  ]
}